dynamicviz/__init__.py
dynamicviz/boot.py
dynamicviz/score.py
dynamicviz/utils.py
dynamicviz/viz.py
dynamicviz-1.0.1.dist-info/LICENSE
dynamicviz-1.0.1.dist-info/WHEEL
dynamicviz-1.0.1.dist-info/METADATA
dynamicviz-1.0.1.dist-info/RECORD
