Metadata-Version: 2.1
Name: dynamicviz
Version: 1.0.1
Summary: DynamicViz provides a wrapper for generating and interpreting dynamic visualizations from traditional static dimensionality reduction visualization methods
Author-email: Eric Sun <edsun97@gmail.com>
Requires-Python: >=3.8
Classifier: License :: OSI Approved :: MIT License
Requires-Dist: dash==2.1.0
Requires-Dist: dash_core_components==2.0.0
Requires-Dist: dash_html_components==2.0.0
Requires-Dist: werkzeug==2.0.3
Requires-Dist: joblib==1.1.0
Requires-Dist: matplotlib==3.5.0
Requires-Dist: numpy==1.21.2
Requires-Dist: numba==0.55.1
Requires-Dist: opencv_python==4.5.5.62
Requires-Dist: pandas==1.3.5
Requires-Dist: Pillow==9.0.1
Requires-Dist: plotly==5.5.0
Requires-Dist: scikit_learn==1.0.2
Requires-Dist: scipy==1.7.3
Requires-Dist: tqdm==4.62.3
Requires-Dist: umap==0.1.1
Requires-Dist: umap_learn==0.5.2
Project-URL: Home, https://github.com/sunericd/dynamicviz
